examples/assistant.py
examples/async_image_feed.py
examples/async_stream.py
examples/async_text_feed.py
examples/discord_bot.py
examples/image_feed.py
examples/stream.py
examples/text_feed.py
examples/transcribe_self.py
pollinations/__init__.py
pollinations/__main__.py
pollinations/cli.py
pollinations/py.typed
pollinations/version.py
pollinations/_core/__init__.py
pollinations/_core/_base_class.py
pollinations/_core/_client.py
pollinations/_core/_consts.py
pollinations/_core/_get_feed_request.py
pollinations/_core/_get_image_request.py
pollinations/_core/_get_stream_request.py
pollinations/_core/_get_text_request.py
pollinations/_core/_get_transcribe_request.py
pollinations/_utils/_clean_params.py
pollinations/_utils/_encode_string.py
pollinations/_utils/_models.py
pollinations/_utils/_prepare_request.py
pollinations/_utils/_stream_process.py
pollinations/_utils/check_file.py
pollinations/_utils/create_message.py
pollinations/_utils/format_image.py
pollinations/_utils/read_image.py
pollinations/_utils/to_pil.py
pollinations/core/feed.py
pollinations/core/image.py
pollinations/core/text.py
pollinations/errors/__init__.py
pollinations/errors/empty_file_error.py
pollinations/errors/failed_to_stream.py
pollinations/errors/failed_to_transcribe.py
pollinations/errors/file_not_found.py
pollinations/errors/improper_permissions.py
pollinations/errors/invalid_or_unkown_prompt.py
pollinations/errors/not_a_file.py
pollinations/helpers/__init__.py
pollinations/helpers/version_check.py
pollinations/types/__init__.py
pollinations/types/aliases.py
pollinations/types/httpx.py
pollinations/types/model.py
pollinations_ai-4.5.1.dist-info/licenses/LICENSE.txt
pollinations_ai-4.5.1.dist-info/METADATA
pollinations_ai-4.5.1.dist-info/WHEEL
pollinations_ai-4.5.1.dist-info/entry_points.txt
pollinations_ai-4.5.1.dist-info/top_level.txt
pollinations_ai-4.5.1.dist-info/RECORD
